caffeine/__init__.py
caffeine/__main__.py
caffeine/applicationinstance.py
caffeine/core.py
caffeine/icons.py
caffeine/inhibitors.py
caffeine/main.py
caffeine/paths.py
caffeine/procmanager.py
caffeine/utils.py
caffeine/version.py
caffeine/assets/glade/GUI.glade
caffeine/assets/glade/proc.glade
caffeine/assets/icons/hicolor/16x16/apps/caffeine.png
caffeine/assets/icons/hicolor/16x16/status/caffeine-cup-empty.png
caffeine/assets/icons/hicolor/16x16/status/caffeine-cup-full.png
caffeine/assets/icons/hicolor/22x22/apps/caffeine.png
caffeine/assets/icons/hicolor/22x22/status/caffeine-cup-empty.png
caffeine/assets/icons/hicolor/22x22/status/caffeine-cup-full.png
caffeine/assets/icons/hicolor/24x24/apps/caffeine.png
caffeine/assets/icons/hicolor/24x24/status/caffeine-cup-empty.png
caffeine/assets/icons/hicolor/24x24/status/caffeine-cup-full.png
caffeine/assets/icons/hicolor/32x32/apps/caffeine.png
caffeine/assets/icons/hicolor/32x32/status/caffeine-cup-empty.png
caffeine/assets/icons/hicolor/32x32/status/caffeine-cup-full.png
caffeine/assets/icons/hicolor/48x48/apps/caffeine.png
caffeine/assets/icons/hicolor/48x48/status/caffeine-cup-empty.png
caffeine/assets/icons/hicolor/48x48/status/caffeine-cup-full.png
caffeine/assets/icons/hicolor/scalable/apps/caffeine.svg
caffeine/assets/icons/hicolor/scalable/status/caffeine-cup-empty.svg
caffeine/assets/icons/hicolor/scalable/status/caffeine-cup-full.svg
caffeine/assets/icons/ubuntu-mono-dark/status/16/caffeine-cup-empty.png
caffeine/assets/icons/ubuntu-mono-dark/status/16/caffeine-cup-full.png
caffeine/assets/icons/ubuntu-mono-dark/status/22/caffeine-cup-empty.png
caffeine/assets/icons/ubuntu-mono-dark/status/22/caffeine-cup-full.png
caffeine/assets/icons/ubuntu-mono-dark/status/24/caffeine-cup-empty.png
caffeine/assets/icons/ubuntu-mono-dark/status/24/caffeine-cup-full.png
caffeine/assets/icons/ubuntu-mono-dark/status/32/caffeine-cup-empty.png
caffeine/assets/icons/ubuntu-mono-dark/status/32/caffeine-cup-full.png
caffeine_ng-3.5.1.dist-info/LICENCE
caffeine_ng-3.5.1.dist-info/METADATA
caffeine_ng-3.5.1.dist-info/WHEEL
caffeine_ng-3.5.1.dist-info/entry_points.txt
caffeine_ng-3.5.1.dist-info/top_level.txt
caffeine_ng-3.5.1.dist-info/RECORD
