Metadata-Version: 2.1
Name: caffeine-ng
Version: 3.5.1
Summary: Tray bar app to temporarily inhibit screensaver and sleep mode.
Home-page: https://github.com/caffeine-ng/caffeine-ng
Author: The Caffeine Developers
Author-email: hugo@barrera.io
Maintainer: Hugo Osvaldo Barrera
Maintainer-email: hugo@barrera.io
License: UNKNOWN
Platform: UNKNOWN
Classifier: Development Status :: 5 - Production/Stable
Classifier: Environment :: X11 Applications
Classifier: Environment :: X11 Applications :: GTK
Classifier: Intended Audience :: End Users/Desktop
Classifier: License :: OSI Approved :: GNU General Public License v3 (GPLv3)
Classifier: Operating System :: POSIX
Classifier: Operating System :: POSIX :: BSD
Classifier: Operating System :: POSIX :: Linux
Classifier: Programming Language :: Python :: 3
Classifier: Programming Language :: Python :: 3.6
Classifier: Programming Language :: Python :: 3.7
Classifier: Programming Language :: Python :: 3.8
Classifier: Programming Language :: Python :: 3.9
Requires-Dist: docopt (>=0.6.2)
Requires-Dist: ewmh (>=0.1.4)
Requires-Dist: pyxdg (>=0.25)
Requires-Dist: setproctitle (>=1.1.10)
Requires-Dist: wheel (>=0.29.0)
Requires-Dist: pulsectl
